unipoll_api/__init__.py
unipoll_api/__version__.py
unipoll_api/account_manager.py
unipoll_api/app.py
unipoll_api/config.py
unipoll_api/dependencies.py
unipoll_api/documents.py
unipoll_api/mongo_db.py
unipoll_api/websocket_manager.py
unipoll_api/actions/__init__.py
unipoll_api/actions/account.py
unipoll_api/actions/authentication.py
unipoll_api/actions/group.py
unipoll_api/actions/members.py
unipoll_api/actions/permissions.py
unipoll_api/actions/policy.py
unipoll_api/actions/poll.py
unipoll_api/actions/superuser.py
unipoll_api/actions/workspace.py
unipoll_api/exceptions/__init__.py
unipoll_api/exceptions/account.py
unipoll_api/exceptions/authentication.py
unipoll_api/exceptions/group.py
unipoll_api/exceptions/policy.py
unipoll_api/exceptions/poll.py
unipoll_api/exceptions/resource.py
unipoll_api/exceptions/workspace.py
unipoll_api/routes/__init__.py
unipoll_api/routes/account.py
unipoll_api/routes/authentication.py
unipoll_api/routes/group.py
unipoll_api/routes/poll.py
unipoll_api/routes/websocket.py
unipoll_api/routes/workspace.py
unipoll_api/schemas/__init__.py
unipoll_api/schemas/account.py
unipoll_api/schemas/authentication.py
unipoll_api/schemas/group.py
unipoll_api/schemas/member.py
unipoll_api/schemas/policy.py
unipoll_api/schemas/poll.py
unipoll_api/schemas/question.py
unipoll_api/schemas/workspace.py
unipoll_api/utils/__init__.py
unipoll_api/utils/auth_strategy.py
unipoll_api/utils/auth_transport.py
unipoll_api/utils/cli_args.py
unipoll_api/utils/colored_dbg.py
unipoll_api/utils/permissions.py
unipoll_api/utils/token_db.py
unipoll_api-0.12.2.dist-info/METADATA
unipoll_api-0.12.2.dist-info/WHEEL
unipoll_api-0.12.2.dist-info/entry_points.txt
unipoll_api-0.12.2.dist-info/top_level.txt
unipoll_api-0.12.2.dist-info/RECORD
