Metadata-Version: 2.1
Name: unipoll-api
Version: 0.12.2
Summary: Unipoll API
Author: University Polling
Author-email: help@unipoll.cc
License: MIT
Classifier: Framework :: FastAPI
Classifier: Programming Language :: Python :: 3
Requires-Python: >=3.11
Requires-Dist: beanie
Requires-Dist: colorama
Requires-Dist: fastapi
Requires-Dist: fastapi-users[beanie]
Requires-Dist: pydantic-settings
Requires-Dist: uvicorn[standard]
Provides-Extra: dev
Requires-Dist: pytest ; extra == 'dev'
Requires-Dist: pytest-cov ; extra == 'dev'
Requires-Dist: faker ; extra == 'dev'
Requires-Dist: flake8 ; extra == 'dev'
Requires-Dist: tox ; extra == 'dev'
Requires-Dist: mypy ; extra == 'dev'
